MANIFEST.in
README.md
setup.py
astron/__init__.py
astron/assests.py
astron/game.py
astron/pre_made.py
astron/scene.py
astron/utilities.py
astron.egg-info/PKG-INFO
astron.egg-info/SOURCES.txt
astron.egg-info/dependency_links.txt
astron.egg-info/requires.txt
astron.egg-info/top_level.txt
astron.egg-info/zip-safe
astron/images/planets.7z
astron/images/ship1 copy.ai
astron/images/ship1.png
astron/images/ship1_+x.png
astron/images/ship1_+y.png
astron/images/ship1_-x.png
astron/images/ship1_-y.png
astron/images/ship1_old.png
astron/images/stars_1.jpg
astron/images/stars_2.jpg
astron/images/stars_3.jpg
astron/images/stars_4.jpg
astron/images/stars_6.jpg
astron/music/Crash_Metal_Plate_Big_Room - planet.mp3
astron/music/Cut_kazoo_full.mp3
astron/music/Raw_Space.mp3
astron/music/Scouting.mp3
astron/music/Space_Trooper.mp3
astron/music/Space_Tunnel.mp3
astron/music/Stuck_In_The_Air.mp3
astron/music/christmas.mp3
astron/music/gottem_full.mp3
astron/music/gottem_vine_cut.mp3
astron/music/kazoo_full.mp3
astron/music/noice.mp3
astron/music/yeet_vine.mp3