Metadata-Version: 1.0
Name: astron
Version: 0.1.9.5
Summary: ...
Home-page: https://www.python.org
Author: Addy Bhatia
Author-email: jude.addy999@gmail.com
License: MIT
Platform: UNKNOWN
